multimatch/__init__.py
multimatch/__main__.py
multimatch/multimatch.py
multimatch/tests/__init__.py
multimatch/tests/test_MultiMatch.py
multimatch/tests/utils.py
multimatch_gaze/__init__.py
multimatch_gaze/__main__.py
multimatch_gaze/multimatch_gaze.py
multimatch_gaze/tests/__init__.py
multimatch_gaze/tests/test_MultiMatch.py
multimatch_gaze/tests/utils.py
multimatch_gaze-0.1.3.dist-info/LICENSE
multimatch_gaze-0.1.3.dist-info/METADATA
multimatch_gaze-0.1.3.dist-info/WHEEL
multimatch_gaze-0.1.3.dist-info/entry_points.txt
multimatch_gaze-0.1.3.dist-info/top_level.txt
multimatch_gaze-0.1.3.dist-info/RECORD
