Metadata-Version: 2.1
Name: multimatch-gaze
Version: 0.1.3
Summary: Multidimensional scan path comparison
Home-page: https://github.com/adswa/multimatch_gaze
Author: Adina Wagner
Author-email: adina.wagner@t-online.de
License: UNKNOWN
Platform: UNKNOWN
Classifier: Programming Language :: Python :: 3
Classifier: License :: OSI Approved :: MIT License
Classifier: Operating System :: OS Independent
Requires-Dist: numpy
Requires-Dist: pandas
Requires-Dist: scipy
Provides-Extra: devel-docs
Requires-Dist: pypandoc ; extra == 'devel-docs'
